IMDbPlayer/__init__.py
IMDbPlayer/__main__.py
IMDbPlayer-1.0.4.dist-info/METADATA
IMDbPlayer-1.0.4.dist-info/WHEEL
IMDbPlayer-1.0.4.dist-info/entry_points.txt
IMDbPlayer-1.0.4.dist-info/top_level.txt
IMDbPlayer-1.0.4.dist-info/RECORD
