Metadata-Version: 2.1
Name: IMDbPlayer
Version: 1.0.4
Summary: A simple script to play movies and TV shows from IMDb using 2embed
Home-page: https://github.com/HmonsterG/2embedPlayer
Author: Eleanor
License: UNKNOWN
Project-URL: Bug Tracker, https://github.com/HmonsterG/2embedPlayer/issues
Platform: UNKNOWN
Classifier: Programming Language :: Python :: 3
Classifier: License :: OSI Approved :: MIT License
Classifier: Operating System :: OS Independent
Requires-Python: >=3.6
